fec2xlsx/__init__.py
fec2xlsx/fec2xlsx.py
fec2xlsx-0.1.2.dist-info/LICENSE
fec2xlsx-0.1.2.dist-info/METADATA
fec2xlsx-0.1.2.dist-info/WHEEL
fec2xlsx-0.1.2.dist-info/top_level.txt
fec2xlsx-0.1.2.dist-info/RECORD
