Metadata-Version: 2.1
Name: fec2xlsx
Version: 0.1.2
Summary: A python library for making Excel files from FEC filings
Home-page: https://github.com/esonderegger/fec2xlsx
Author: Evan Sonderegger
Author-email: evan@rpy.xyz
License: MIT
Project-URL: Bug Tracker, https://github.com/esonderegger/fec2xlsx/issues
Project-URL: Source Code, https://github.com/esonderegger/fec2xlsx/
Keywords: fec campaign finance politics
Platform: UNKNOWN
Classifier: Development Status :: 3 - Alpha
Classifier: Environment :: Console
Classifier: Intended Audience :: Developers
Classifier: License :: OSI Approved :: MIT License
Classifier: Operating System :: OS Independent
Classifier: Programming Language :: Python
Requires-Dist: fecfile (>=0.6.1)
Requires-Dist: XlsxWriter (>=1.1.6)
